Workbook

Sheet markets
A1: country | B1: region | C1: market_size_musd | D1: cagr | E1: competition_index | F1: fixed_cost_musd | G1: min_spend_musd | H1: max_spend_musd | I1: risk_weight
A2: =calc!A5 -> United Kingdom | B2: =calc!B5 -> Europe | C2: =calc!C5 -> 811.657 | D2: =calc!D5 -> 0.25419754 | E2: =calc!E5 -> 0.5 | F2: =calc!F5 -> 16.23314 | G2: =calc!G5 -> 64.93256 | H2: =calc!H5 -> 284.07995 | I2: =calc!I5 -> 0.58651804
A3: =calc!A6 -> Norway | B3: =calc!B6 -> Europe | C3: =calc!C6 -> 324.3 | D3: =calc!D6 -> 0.19854664 | E3: =calc!E6 -> 0.5 | F3: =calc!F6 -> 6.486 | G3: =calc!G6 -> 25.944 | H3: =calc!H6 -> 113.505 | I3: =calc!I6 -> 0.65465794
A4: =calc!A7 -> Spain | B4: =calc!B7 -> Europe | C4: =calc!C7 -> 113.94 | D4: =calc!D7 -> 0.40957556 | E4: =calc!E7 -> 0.5 | F4: =calc!F7 -> 2.2788 | G4: =calc!G7 -> 9.1152 | H4: =calc!H7 -> 39.879 | I4: =calc!I7 -> 0.68406946
A5: =calc!A8 -> Finland | B5: =calc!B8 -> Europe | C5: =calc!C8 -> 93.258 | D5: =calc!D8 -> 0.35229448 | E5: =calc!E8 -> 0.5 | F5: =calc!F8 -> 1.86516 | G5: =calc!G8 -> 7.46064 | H5: =calc!H8 -> 32.6403 | I5: =calc!I8 -> 0.68696112
A6: =calc!A9 -> Germany | B6: =calc!B9 -> Europe | C6: =calc!C9 -> 2860.92 | D6: =calc!D9 -> 0.33719305 | E6: =calc!E9 -> 0.5 | F6: =calc!F9 -> 57.2184 | G6: =calc!G9 -> 228.8736 | H6: =calc!H9 -> 1001.322 | I6: =calc!I9 -> 0.3
A7: =calc!A10 -> Estonia | B7: =calc!B10 -> Europe | C7: =calc!C10 -> 7.70796 | D7: =calc!D10 -> 0.58946407 | E7: =calc!E10 -> 0.5 | F7: =calc!F10 -> 0.25 | G7: =calc!G10 -> 1 | H7: =calc!H10 -> 2.697786 | I7: =calc!I10 -> 0.69892231
A8: =calc!A11 -> Latvia | B8: =calc!B11 -> Europe | C8: =calc!C11 -> 6.9336 | D8: =calc!D11 -> 0.59453405 | E8: =calc!E11 -> 0.5 | F8: =calc!F11 -> 0.25 | G8: =calc!G11 -> 1 | H8: =calc!H11 -> 2.42676 | I8: =calc!I11 -> 0.69903058
A9: =calc!A12 -> Iceland | B9: =calc!B12 -> Europe | C9: =calc!C12 -> 21.438 | D9: =calc!D12 -> 0.25296957 | E9: =calc!E12 -> 0.5 | F9: =calc!F12 -> 0.42876 | G9: =calc!G12 -> 1.71504 | H9: =calc!H12 -> 7.5033 | I9: =calc!I12 -> 0.69700264
A10: =calc!A13 -> Denmark | B10: =calc!B13 -> Europe | C10: =calc!C13 -> 254.988 | D10: =calc!D13 -> 0.31063798 | E10: =calc!E13 -> 0.5 | F10: =calc!F13 -> 5.09976 | G10: =calc!G13 -> 20.39904 | H10: =calc!H13 -> 89.2458 | I10: =calc!I13 -> 0.66434881

Sheet assumptions
A1: MarketSelect inputs
A2: Yellow cells are assumptions, not Statista figures. Change them and the calc sheet updates.
A4: FX assumption | B4: USD per 1 unit | C4: Note
A5: EUR | B5: 1.08 | C5: Assumption used for this file. Not a Statista rate and not a live rate.
A6: GBP | B6: 1.27 | C6: Assumption used for this file. Not a Statista rate and not a live rate.
A7: USD | B7: 1 | C7: Norway file is already in million USD.
A9: Model assumption | B9: Value | C9: Note
A10: competition_index | B10: 0.5 | C10: Placeholder. No EVs-per-charger file was supplied, so this does not come from Statista.
A11: min spend share of market | B11: 0.08 | C11: Floor of 1 million USD. Not from Statista.
A12: max spend share of market | B12: 0.35 | C12: Cap so a large market cannot absorb the whole budget by assumption. Not from Statista.
A13: fixed cost share of min spend | B13: 0.25 | C13: Entry cost. Not from Statista.
A14: base risk weight | B14: 0.3 | C14: Applied to the largest market. Smaller markets get a higher weight.
A15: small-market risk add-on | B15: 0.4 | C15: Added as market size falls toward the smallest country.

Sheet source
A1: Statista source series
A2: Values are the published series from the uploaded XLS files. Estonia and Latvia are converted from thousand euros to million euros here.
A4: country | B4: region | C4: statista_id | D4: unit_as_published | E4: base_year | F4: forecast_year | G4: base_local | H4: forecast_local | I4: local_unit | J4: fx_code | K4: years | L4: url
A5: United Kingdom | B5: Europe | C5: 1411503 | D5: million GBP | E5: 2023 | F5: 2029 | G5: 164.2 | H5: 639.1 | I5: million GBP | J5: GBP | K5: =F5-E5 -> 6
A6: Norway | B6: Europe | C6: 1413409 | D6: million USD | E6: 2023 | F6: 2029 | G6: 109.4 | H6: 324.3 | I6: million USD | J6: USD | K6: =F6-E6 -> 6
A7: Spain | B7: Europe | C7: 1441469 | D7: million EUR | E7: 2022 | F7: 2028 | G7: 13.45 | H7: 105.5 | I7: million EUR | J7: EUR | K7: =F7-E7 -> 6
A8: Finland | B8: Europe | C8: 1477322 | D8: million EUR | E8: 2023 | F8: 2029 | G8: 14.12 | H8: 86.35 | I8: million EUR | J8: EUR | K8: =F8-E8 -> 6
A9: Germany | B9: Europe | C9: 1484167 | D9: million EUR | E9: 2023 | F9: 2028 | G9: 619.6 | H9: 2649 | I9: million EUR | J9: EUR | K9: =F9-E9 -> 5
A10: Estonia | B10: Europe | C10: 1499736 | D10: thousand EUR | E10: 2023 | F10: 2029 | G10: 0.4426 | H10: 7.137 | I10: million EUR | J10: EUR | K10: =F10-E10 -> 6
A11: Latvia | B11: Europe | C11: 1499740 | D11: thousand EUR | E11: 2023 | F11: 2029 | G11: 0.3906 | H11: 6.42 | I11: million EUR | J11: EUR | K11: =F11-E11 -> 6
A12: Iceland | B12: Europe | C12: 1553214 | D12: million EUR | E12: 2023 | F12: 2029 | G12: 5.13 | H12: 19.85 | I12: million EUR | J12: EUR | K12: =F12-E12 -> 6
A13: Denmark | B13: Europe | C13: 1553215 | D13: million EUR | E13: 2023 | F13: 2029 | G13: 46.58 | H13: 236.1 | I13: million EUR | J13: EUR | K13: =F13-E13 -> 6

Sheet calc
A1: Model panel, formula-driven
A2: Upload the markets sheet to the app. This sheet is the audit trail. CAGR uses the base year and forecast year on the source sheet, which are not the same for every country.
A4: country | B4: region | C4: market_size_musd | D4: cagr | E4: competition_index | F4: fixed_cost_musd | G4: min_spend_musd | H4: max_spend_musd | I4: risk_weight | J4: statista_id | K4: base_year | L4: forecast_year
A5: =source!A5 -> United Kingdom | B5: =source!B5 -> Europe | C5: =source!H5*IF(source!J5="EUR",assumptions!$B$5,IF(source!J5="GBP",assumptions!$B$6,assumptions!$B$7)) -> 811.657 | D5: =(source!H5/source!G5)^(1/source!K5)-1 -> 0.25419754 | E5: =assumptions!$B$10 -> 0.5 | F5: =assumptions!$B$13*G5 -> 16.23314 | G5: =MAX(1,assumptions!$B$11*C5) -> 64.93256 | H5: =MAX(G5,assumptions!$B$12*C5) -> 284.07995 | I5: =assumptions!$B$14+assumptions!$B$15*(1-C5/MAX($C$5:$C$13)) -> 0.58651804 | J5: =source!C5 -> 1411503 | K5: =source!E5 -> 2023 | L5: =source!F5 -> 2029
A6: =source!A6 -> Norway | B6: =source!B6 -> Europe | C6: =source!H6*IF(source!J6="EUR",assumptions!$B$5,IF(source!J6="GBP",assumptions!$B$6,assumptions!$B$7)) -> 324.3 | D6: =(source!H6/source!G6)^(1/source!K6)-1 -> 0.19854664 | E6: =assumptions!$B$10 -> 0.5 | F6: =assumptions!$B$13*G6 -> 6.486 | G6: =MAX(1,assumptions!$B$11*C6) -> 25.944 | H6: =MAX(G6,assumptions!$B$12*C6) -> 113.505 | I6: =assumptions!$B$14+assumptions!$B$15*(1-C6/MAX($C$5:$C$13)) -> 0.65465794 | J6: =source!C6 -> 1413409 | K6: =source!E6 -> 2023 | L6: =source!F6 -> 2029
A7: =source!A7 -> Spain | B7: =source!B7 -> Europe | C7: =source!H7*IF(source!J7="EUR",assumptions!$B$5,IF(source!J7="GBP",assumptions!$B$6,assumptions!$B$7)) -> 113.94 | D7: =(source!H7/source!G7)^(1/source!K7)-1 -> 0.40957556 | E7: =assumptions!$B$10 -> 0.5 | F7: =assumptions!$B$13*G7 -> 2.2788 | G7: =MAX(1,assumptions!$B$11*C7) -> 9.1152 | H7: =MAX(G7,assumptions!$B$12*C7) -> 39.879 | I7: =assumptions!$B$14+assumptions!$B$15*(1-C7/MAX($C$5:$C$13)) -> 0.68406946 | J7: =source!C7 -> 1441469 | K7: =source!E7 -> 2022 | L7: =source!F7 -> 2028
A8: =source!A8 -> Finland | B8: =source!B8 -> Europe | C8: =source!H8*IF(source!J8="EUR",assumptions!$B$5,IF(source!J8="GBP",assumptions!$B$6,assumptions!$B$7)) -> 93.258 | D8: =(source!H8/source!G8)^(1/source!K8)-1 -> 0.35229448 | E8: =assumptions!$B$10 -> 0.5 | F8: =assumptions!$B$13*G8 -> 1.86516 | G8: =MAX(1,assumptions!$B$11*C8) -> 7.46064 | H8: =MAX(G8,assumptions!$B$12*C8) -> 32.6403 | I8: =assumptions!$B$14+assumptions!$B$15*(1-C8/MAX($C$5:$C$13)) -> 0.68696112 | J8: =source!C8 -> 1477322 | K8: =source!E8 -> 2023 | L8: =source!F8 -> 2029
A9: =source!A9 -> Germany | B9: =source!B9 -> Europe | C9: =source!H9*IF(source!J9="EUR",assumptions!$B$5,IF(source!J9="GBP",assumptions!$B$6,assumptions!$B$7)) -> 2860.92 | D9: =(source!H9/source!G9)^(1/source!K9)-1 -> 0.33719305 | E9: =assumptions!$B$10 -> 0.5 | F9: =assumptions!$B$13*G9 -> 57.2184 | G9: =MAX(1,assumptions!$B$11*C9) -> 228.8736 | H9: =MAX(G9,assumptions!$B$12*C9) -> 1001.322 | I9: =assumptions!$B$14+assumptions!$B$15*(1-C9/MAX($C$5:$C$13)) -> 0.3 | J9: =source!C9 -> 1484167 | K9: =source!E9 -> 2023 | L9: =source!F9 -> 2028
A10: =source!A10 -> Estonia | B10: =source!B10 -> Europe | C10: =source!H10*IF(source!J10="EUR",assumptions!$B$5,IF(source!J10="GBP",assumptions!$B$6,assumptions!$B$7)) -> 7.70796 | D10: =(source!H10/source!G10)^(1/source!K10)-1 -> 0.58946407 | E10: =assumptions!$B$10 -> 0.5 | F10: =assumptions!$B$13*G10 -> 0.25 | G10: =MAX(1,assumptions!$B$11*C10) -> 1 | H10: =MAX(G10,assumptions!$B$12*C10) -> 2.697786 | I10: =assumptions!$B$14+assumptions!$B$15*(1-C10/MAX($C$5:$C$13)) -> 0.69892231 | J10: =source!C10 -> 1499736 | K10: =source!E10 -> 2023 | L10: =source!F10 -> 2029
A11: =source!A11 -> Latvia | B11: =source!B11 -> Europe | C11: =source!H11*IF(source!J11="EUR",assumptions!$B$5,IF(source!J11="GBP",assumptions!$B$6,assumptions!$B$7)) -> 6.9336 | D11: =(source!H11/source!G11)^(1/source!K11)-1 -> 0.59453405 | E11: =assumptions!$B$10 -> 0.5 | F11: =assumptions!$B$13*G11 -> 0.25 | G11: =MAX(1,assumptions!$B$11*C11) -> 1 | H11: =MAX(G11,assumptions!$B$12*C11) -> 2.42676 | I11: =assumptions!$B$14+assumptions!$B$15*(1-C11/MAX($C$5:$C$13)) -> 0.69903058 | J11: =source!C11 -> 1499740 | K11: =source!E11 -> 2023 | L11: =source!F11 -> 2029
A12: =source!A12 -> Iceland | B12: =source!B12 -> Europe | C12: =source!H12*IF(source!J12="EUR",assumptions!$B$5,IF(source!J12="GBP",assumptions!$B$6,assumptions!$B$7)) -> 21.438 | D12: =(source!H12/source!G12)^(1/source!K12)-1 -> 0.25296957 | E12: =assumptions!$B$10 -> 0.5 | F12: =assumptions!$B$13*G12 -> 0.42876 | G12: =MAX(1,assumptions!$B$11*C12) -> 1.71504 | H12: =MAX(G12,assumptions!$B$12*C12) -> 7.5033 | I12: =assumptions!$B$14+assumptions!$B$15*(1-C12/MAX($C$5:$C$13)) -> 0.69700264 | J12: =source!C12 -> 1553214 | K12: =source!E12 -> 2023 | L12: =source!F12 -> 2029
A13: =source!A13 -> Denmark | B13: =source!B13 -> Europe | C13: =source!H13*IF(source!J13="EUR",assumptions!$B$5,IF(source!J13="GBP",assumptions!$B$6,assumptions!$B$7)) -> 254.988 | D13: =(source!H13/source!G13)^(1/source!K13)-1 -> 0.31063798 | E13: =assumptions!$B$10 -> 0.5 | F13: =assumptions!$B$13*G13 -> 5.09976 | G13: =MAX(1,assumptions!$B$11*C13) -> 20.39904 | H13: =MAX(G13,assumptions!$B$12*C13) -> 89.2458 | I13: =assumptions!$B$14+assumptions!$B$15*(1-C13/MAX($C$5:$C$13)) -> 0.66434881 | J13: =source!C13 -> 1553215 | K13: =source!E13 -> 2023 | L13: =source!F13 -> 2029

Sheet citations
A1: Citations
A2: Source for every revenue figure: Statista Mobility Market Insights, via the statistic id below. Do not cite the spend bounds or competition index as Statista.
A4: country | B4: statista_id | C4: statistic_title | D4: unit | E4: base_to_forecast | F4: url | G4: publication
A5: =source!A5 -> United Kingdom | B5: =source!C5 -> 1411503 | C5: Projected electric vehicle charging station revenue in the United Kingdom between 2016 and 2029 | D5: =source!D5 -> million GBP | E5: =source!E5&"-"&source!F5 -> 2023-2029 | F5: =source!L5 -> 0 | G5: Nov 2024
A6: =source!A6 -> Norway | B6: =source!C6 -> 1413409 | C6: Projected electric vehicle charging station revenue in Norway between 2016 and 2029 | D6: =source!D6 -> million USD | E6: =source!E6&"-"&source!F6 -> 2023-2029 | F6: =source!L6 -> 0 | G6: Aug 2024
A7: =source!A7 -> Spain | B7: =source!C7 -> 1441469 | C7: Public charging station revenue in Spain between 2016 and 2022, with a forecast through 2028 | D7: =source!D7 -> million EUR | E7: =source!E7&"-"&source!F7 -> 2022-2028 | F7: =source!L7 -> 0 | G7: Aug 2023
A8: =source!A8 -> Finland | B8: =source!C8 -> 1477322 | C8: Revenue from public electric vehicle charging stations in Finland from 2016 to 2023, with a forecast through 2029 | D8: =source!D8 -> million EUR | E8: =source!E8&"-"&source!F8 -> 2023-2029 | F8: =source!L8 -> 0 | G8: Nov 2024
A9: =source!A9 -> Germany | B9: =source!C9 -> 1484167 | C9: Projected public electric vehicle charging station revenue in Germany between 2016 and 2028 | D9: =source!D9 -> million EUR | E9: =source!E9&"-"&source!F9 -> 2023-2028 | F9: =source!L9 -> 0 | G9: Aug 2023
A10: =source!A10 -> Estonia | B10: =source!C10 -> 1499736 | C10: Projected public electric vehicle charging station revenue in Estonia between 2016 and 2029 | D10: =source!D10 -> thousand EUR | E10: =source!E10&"-"&source!F10 -> 2023-2029 | F10: =source!L10 -> 0 | G10: Jul 2024
A11: =source!A11 -> Latvia | B11: =source!C11 -> 1499740 | C11: Projected public electric vehicle charging station revenue in Latvia between 2016 and 2029 | D11: =source!D11 -> thousand EUR | E11: =source!E11&"-"&source!F11 -> 2023-2029 | F11: =source!L11 -> 0 | G11: Jul 2024
A12: =source!A12 -> Iceland | B12: =source!C12 -> 1553214 | C12: Projected public electric vehicle charging revenue in Iceland between 2016 and 2029 | D12: =source!D12 -> million EUR | E12: =source!E12&"-"&source!F12 -> 2023-2029 | F12: =source!L12 -> 0 | G12: Oct 2024
A13: =source!A13 -> Denmark | B13: =source!C13 -> 1553215 | C13: Projected public electric vehicle charging revenue in Denmark between 2016 and 2029 | D13: =source!D13 -> million EUR | E13: =source!E13&"-"&source!F13 -> 2023-2029 | F13: =source!L13 -> 0 | G13: Oct 2024
